{
  "orders": [
    {
      "id": 1,
      "bill-to": "MSH",
      "ship-to": "New York",
      "model": "Liz Lemon",
      "quantity": 36,
      "price": 10.5,
      "order_status": "Booked",
      "line_status": "Booked",
      "customer_po": 30486
    },
    {
      "id": 2,
      "bill-to": "MSH",
      "ship-to": "New York",
      "model": "Jack Donaghy",
      "quantity": 40,
      "price": 115.5,
      "order_status": "Booked",
      "line_status": "Awaiting Shipping",
      "customer_po": 30486
    },
    {
      "id": 3,
      "bill-to": "MSH",
      "ship-to": "New York",
      "model": "Tracy Morgan",
      "quantity": 39,
      "price": 125.8,
      "order_status": "Booked",
      "line_status": "Pending Pre-Billing",
      "customer_po": 30486
    },
    {
      "id": 4,
      "bill-to": "MSH",
      "ship-to": "New York",
      "model": "Jenna Maroney",
      "quantity": 40,
      "price": 119.85,
      "order_status": "Booked",
      "line_status": "Closed",
      "customer_po": 30486
    },
    {
      "id": 6,
      "bill-to": "Saturn",
      "ship-to": "Boston",
      "model": "Pete Hornberger",
      "quantity": 28,
      "price": 13.57,
      "order_status": "Entered",
      "line_status": "Booked",
      "customer_po": 21577
    },
    {
      "id": 5,
      "bill-to": "MSH",
      "ship-to": "New York",
      "model": "Kenneth Parcell",
      "quantity": 18,
      "price": 76.45,
      "order_status": "Booked",
      "line_status": "Awaiting Shipping",
      "customer_po": 30486
    },
    {
      "id": 7,
      "bill-to": "Saturn",
      "ship-to": "Boston",
      "model": "Frank Rossitano",
      "quantity": 36,
      "price": 67.85,
      "order_status": "Entered",
      "line_status": "Entered",
      "customer_po": 21577
    },
    {
      "id": 8,
      "bill-to": "Saturn",
      "ship-to": "Boston",
      "model": "Havier Romano",
      "quantity": 80,
      "price": 80.5,
      "order_status": "Entered",
      "line_status": "Booked",
      "customer_po": 21577
    },
    {
      "bill-to": "asdf",
      "ship-to": "asdf",
      "model": "asdf",
      "quantity": "asdf",
      "price": "asdf",
      "order_status": "Booked",
      "line_status": "Booked",
      "customer_po": "asdf",
      "id": 9
    }
  ]
}